seshkit/__init__.py
seshkit/cli.py
seshkit/cmds/config.py
seshkit/types/path.py
seshkit-0.0.1.dist-info/LICENSE
seshkit-0.0.1.dist-info/METADATA
seshkit-0.0.1.dist-info/WHEEL
seshkit-0.0.1.dist-info/entry_points.txt
seshkit-0.0.1.dist-info/top_level.txt
seshkit-0.0.1.dist-info/RECORD
