Metadata-Version: 2.1
Name: seshkit
Version: 0.0.1
Summary: seshkit is a command-line tool for creating transcripts from audio files.
Home-page: https://github.com/dannguyen/seshkit
Author: Dan Nguyen
Author-email: dansonguyen@gmail.com
License: MIT license
Keywords: seshkit
Platform: UNKNOWN
Classifier: Development Status :: 2 - Pre-Alpha
Classifier: Intended Audience :: Developers
Classifier: License :: OSI Approved :: MIT License
Classifier: Natural Language :: English
Classifier: Programming Language :: Python :: 3
Classifier: Programming Language :: Python :: 3.6
Classifier: Programming Language :: Python :: 3.7
Classifier: Programming Language :: Python :: 3.8
Requires-Python: >=3.5
Requires-Dist: boto3 (>=1.15)
Requires-Dist: Click (>=7.0)
Requires-Dist: colorama
Requires-Dist: requests
